hawk/__init__.py
hawk/agent.py
hawk/app.py
hawk/config.py
hawk/main.py
hawk/replicate_client.py
hawk/splash.py
hawk/video.py
hawk/screens/__init__.py
hawk/screens/preview.py
hawk/screens/splash.py
hawk/widgets/__init__.py
hawk_tui_video-1.0.0.dist-info/METADATA
hawk_tui_video-1.0.0.dist-info/WHEEL
hawk_tui_video-1.0.0.dist-info/entry_points.txt
hawk_tui_video-1.0.0.dist-info/licenses/LICENSE
hawk_tui_video-1.0.0.dist-info/RECORD
