Metadata-Version: 2.4
Name: hawk-tui-video
Version: 1.0.0
Summary: Terminal-based TikTok video creator with AI image generation
Project-URL: Homepage, https://hawktui.xyz
Project-URL: Repository, https://github.com/carsonmulligan/hawktui
Project-URL: Documentation, https://hawktui.xyz
Author: Carson Mulligan
License: MIT
License-File: LICENSE
Keywords: ai,cli,replicate,terminal,tiktok,tui,video
Classifier: Development Status :: 4 - Beta
Classifier: Environment :: Console
Classifier: Intended Audience :: Developers
Classifier: Intended Audience :: End Users/Desktop
Classifier: License :: OSI Approved :: MIT License
Classifier: Operating System :: OS Independent
Classifier: Programming Language :: Python :: 3
Classifier: Programming Language :: Python :: 3.11
Classifier: Programming Language :: Python :: 3.12
Classifier: Topic :: Multimedia :: Video
Requires-Python: >=3.11
Requires-Dist: httpx>=0.27.0
Requires-Dist: pillow>=10.0.0
Requires-Dist: python-dotenv>=1.0.0
Requires-Dist: replicate>=0.25.0
Requires-Dist: rich>=13.0.0
Requires-Dist: textual>=0.50.0
